adzuki/__init__.py
adzuki/entitywrapper.py
adzuki/model.py
adzuki/utils.py
adzuki-0.2.1.dist-info/LICENSE
adzuki-0.2.1.dist-info/METADATA
adzuki-0.2.1.dist-info/WHEEL
adzuki-0.2.1.dist-info/top_level.txt
adzuki-0.2.1.dist-info/RECORD
