Metadata-Version: 2.1
Name: adzuki
Version: 0.2.1
Summary: ORM for GCP datastore
Home-page: https://github.com/showhue/adzuki/
Author: SHOWHUE, Ire Sun, Kunda Lee
Author-email: ire7715+adzuki@hotmail.com
License: UNKNOWN
Platform: UNKNOWN
Classifier: Programming Language :: Python :: 3
Classifier: License :: OSI Approved :: BSD License
Classifier: Operating System :: OS Independent
Requires-Dist: jsonschema (>=3.0.1)
Requires-Dist: google-cloud-datastore (>=1.7.3)
